setup.py
bin/pystocker
pystocker/__init__.py
pystocker/permanents.py
pystocker/stocks.py
pystocker/user_input.py
pystocker/ystockquote.py
pystocker.egg-info/PKG-INFO
pystocker.egg-info/SOURCES.txt
pystocker.egg-info/dependency_links.txt
pystocker.egg-info/top_level.txt