Metadata-Version: 1.0
Name: pystocker
Version: 0.1.25
Summary: lightweight ncurses stock tracker
Home-page: http://github.com/coffeeandscripts/pystock
Author: coffeeandscripts
Author-email: ersari94@gmail.com
License: GNU
Platform: UNKNOWN
